fastjsonrpc/__init__.py
fastjsonrpc/client.py
fastjsonrpc/jsonrpc.py
fastjsonrpc/netstringclient.py
fastjsonrpc/netstringserver.py
fastjsonrpc/server.py
quickjsonrpc-0.4.0.dist-info/LICENSE
quickjsonrpc-0.4.0.dist-info/WHEEL
quickjsonrpc-0.4.0.dist-info/METADATA
quickjsonrpc-0.4.0.dist-info/RECORD
